Metadata-Version: 2.1
Name: instastalk
Version: 0.1.15
Summary: Download your instacrush posts
Home-page: https://github.com/jjkoh95/instastalk
Author: jjkoh95
Author-email: jjkoh95@gmail.com
License: MIT
Keywords: instagram,scrape
Platform: UNKNOWN
Classifier: Development Status :: 3 - Alpha
Classifier: Intended Audience :: Developers
Classifier: Topic :: Software Development :: Build Tools
Classifier: License :: OSI Approved :: MIT License
Classifier: Programming Language :: Python :: 3.7
